skylight_sdk/__init__.py
skylight_sdk/_hooks/__init__.py
skylight_sdk/_hooks/registration.py
skylight_sdk/_hooks/sdkhooks.py
skylight_sdk/_hooks/types.py
skylight_sdk/_version.py
skylight_sdk/agent.py
skylight_sdk/basesdk.py
skylight_sdk/files.py
skylight_sdk/httpclient.py
skylight_sdk/interact.py
skylight_sdk/models/__init__.py
skylight_sdk/models/activeoperationresponse.py
skylight_sdk/models/agentstatusresponse.py
skylight_sdk/models/answerop.py
skylight_sdk/models/apierror.py
skylight_sdk/models/clauderequest.py
skylight_sdk/models/clickop.py
skylight_sdk/models/clickrequest.py
skylight_sdk/models/downloadop.py
skylight_sdk/models/dragop.py
skylight_sdk/models/dragrequest.py
skylight_sdk/models/filedownloadresponse.py
skylight_sdk/models/fileuploadresponse.py
skylight_sdk/models/forbiddenerrorresponse.py
skylight_sdk/models/httpvalidationerror.py
skylight_sdk/models/inactiveoperationresponse.py
skylight_sdk/models/installop.py
skylight_sdk/models/instancerequest.py
skylight_sdk/models/instanceslistresponse.py
skylight_sdk/models/instancestartresponse.py
skylight_sdk/models/instancestatusresponse.py
skylight_sdk/models/interact_models_errorresponse.py
skylight_sdk/models/keypressop.py
skylight_sdk/models/keyrequest.py
skylight_sdk/models/mousemoverequest.py
skylight_sdk/models/moveop.py
skylight_sdk/models/packageinstallrequest.py
skylight_sdk/models/packageinstallresponse.py
skylight_sdk/models/pauseop.py
skylight_sdk/models/resumeop.py
skylight_sdk/models/runop.py
skylight_sdk/models/s3vmuploadrequest.py
skylight_sdk/models/screenshotop.py
skylight_sdk/models/screenshotresponse.py
skylight_sdk/models/scrollop.py
skylight_sdk/models/scrollrequest.py
skylight_sdk/models/security.py
skylight_sdk/models/standardresponse.py
skylight_sdk/models/stateop.py
skylight_sdk/models/statusop.py
skylight_sdk/models/stopop.py
skylight_sdk/models/terminateop.py
skylight_sdk/models/typeop.py
skylight_sdk/models/typerequest.py
skylight_sdk/models/uploadop.py
skylight_sdk-0.1.0.dist-info/METADATA
skylight_sdk-0.1.0.dist-info/WHEEL
skylight_sdk-0.1.0.dist-info/RECORD
